HISTORY.txt
LICENSE
MANIFEST.in
README.md
pyproject.toml
requirements.txt
setup.py
mmcif/__init__.py
mmcif.sitegen.egg-info/PKG-INFO
mmcif.sitegen.egg-info/SOURCES.txt
mmcif.sitegen.egg-info/dependency_links.txt
mmcif.sitegen.egg-info/entry_points.txt
mmcif.sitegen.egg-info/not-zip-safe
mmcif.sitegen.egg-info/requires.txt
mmcif.sitegen.egg-info/top_level.txt
mmcif/sitegen/__init__.py
mmcif/sitegen/dictionary/DictionaryFileUtils.py
mmcif/sitegen/dictionary/DictionaryItemCoverage.py
mmcif/sitegen/dictionary/DictionaryRegistry.py
mmcif/sitegen/dictionary/HtmlContentUtils.py
mmcif/sitegen/dictionary/HtmlGenerator.py
mmcif/sitegen/dictionary/HtmlMarkupUtils.py
mmcif/sitegen/dictionary/HtmlPathInfo.py
mmcif/sitegen/dictionary/NeighborFigures.py
mmcif/sitegen/dictionary/__init__.py
mmcif/sitegen/wf/HtmlGeneratorWf.py
mmcif/sitegen/wf/NeighborFiguresWf.py
mmcif/sitegen/wf/SiteGeneratorExec.py
mmcif/sitegen/wf/__init__.py